fillpdf/__init__.py
fillpdf/extractfillpdf.py
fillpdf/fillpdfs.py
fillpdf/insertfillpdf.py
fillpdf-0.7.0.dist-info/LICENSE
fillpdf-0.7.0.dist-info/METADATA
fillpdf-0.7.0.dist-info/WHEEL
fillpdf-0.7.0.dist-info/entry_points.txt
fillpdf-0.7.0.dist-info/top_level.txt
fillpdf-0.7.0.dist-info/RECORD
