Metadata-Version: 2.1
Name: fillpdf
Version: 0.7.0
Summary: A Library to fill and flatten pdfs
Home-page: https://github.com/t-houssian/fillpdf
Author: Tyler Houssian
Author-email: tylerhoussian@gmail.com
License: UNKNOWN
Platform: UNKNOWN
Classifier: Programming Language :: Python :: 3
Classifier: License :: OSI Approved :: MIT License
Classifier: Operating System :: OS Independent
Requires-Python: >=3.6
License-File: LICENSE
Requires-Dist: pdfrw2
Requires-Dist: pdf2image
Requires-Dist: Pillow
Requires-Dist: pymupdf
